shoestring_setup/__init__.py
shoestring_setup/apt_deps.py
shoestring_setup/cli.py
shoestring_setup/display.py
shoestring_setup/docker.py
shoestring_setup/logrotate.py
shoestring_setup/operations.py
shoestring_setup/rsyslog.py
shoestring_setup/shoestring_assembler.py
shoestring_setup/shoestring_setup.py
shoestring_setup/assets/__init__.py
shoestring_setup/assets/shoestring_logo.png
shoestring_setup-0.2.8.dist-info/licenses/LICENSE
shoestring_setup-0.2.8.dist-info/METADATA
shoestring_setup-0.2.8.dist-info/WHEEL
shoestring_setup-0.2.8.dist-info/entry_points.txt
shoestring_setup-0.2.8.dist-info/top_level.txt
shoestring_setup-0.2.8.dist-info/RECORD
