Metadata-Version: 2.4
Name: shoestring_setup
Version: 0.2.8
Summary: Installs dependencies needed to run shoestring solutions
Author-email: Greg Hawkridge <gth24@cam.ac.uk>
Maintainer-email: Greg Hawkridge <gth24@cam.ac.uk>
Project-URL: issues, https://github.com/DigitalShoestringSolutions/shoestring_setup/issues
Project-URL: changelog, https://github.com/DigitalShoestringSolutions/shoestring_setup/blob/main/changelog.md
Project-URL: homepage, https://github.com/DigitalShoestringSolutions/shoestring_setup
Project-URL: source, https://github.com/DigitalShoestringSolutions/shoestring_setup
Keywords: shoestring,manufacturing,installer
Classifier: Development Status :: 1 - Planning
Classifier: Environment :: Console
Classifier: Operating System :: POSIX :: Linux
Classifier: License :: OSI Approved :: GNU General Public License v3 (GPLv3)
Classifier: Intended Audience :: End Users/Desktop
Classifier: Topic :: System :: Software Distribution
Requires-Python: >=3.10
License-File: LICENSE
Requires-Dist: typer==0.19.2
Provides-Extra: dev
Requires-Dist: coverage; extra == "dev"
Requires-Dist: mypy; extra == "dev"
Requires-Dist: pytest; extra == "dev"
Requires-Dist: ruff; extra == "dev"
Dynamic: license-file
